{"lastUsed":1590560865408,"path":"C:\/src\/jspwork","projectCount":5,"recentFiles":[{"path":"\/Chapter3\/src","parentWorkspace":"C:\/src\/jspwork","name":"BoardListServlet.java","lastModified":1590470688367,"locationURI":"file:\/C:\/src\/jspwork\/Chapter3\/src\/BoardListServlet.java"},{"path":"\/Chapter3\/src","parentWorkspace":"C:\/src\/jspwork","name":"HangulServlet.java","lastModified":1590474189095,"locationURI":"file:\/C:\/src\/jspwork\/Chapter3\/src\/HangulServlet.java"},{"path":"\/random\/src\/random","parentWorkspace":"C:\/src\/jspwork","name":"App.java","lastModified":1590560865409,"locationURI":"file:\/C:\/src\/jspwork\/random\/src\/random\/App.java"},{"path":"\/Chapter3\/src","parentWorkspace":"C:\/src\/jspwork","name":"SetNameServlet.java","lastModified":1590476609582,"locationURI":"file:\/C:\/src\/jspwork\/Chapter3\/src\/SetNameServlet.java"},{"path":"\/ch04\/WebContent","parentWorkspace":"C:\/src\/jspwork","name":"scriptletTest.jsp","lastModified":1590545601413,"locationURI":"file:\/C:\/src\/jspwork\/ch04\/WebContent\/scriptletTest.jsp"},{"path":"\/Chapter3\/WebContent","parentWorkspace":"C:\/src\/jspwork","name":"login.jsp","lastModified":1590476884090,"locationURI":"file:\/C:\/src\/jspwork\/Chapter3\/WebContent\/login.jsp"},{"path":"\/ch04\/WebContent","parentWorkspace":"C:\/src\/jspwork","name":"joinError.jsp","lastModified":1590555643110,"locationURI":"file:\/C:\/src\/jspwork\/ch04\/WebContent\/joinError.jsp"},{"path":"\/Chapter3\/WebContent","parentWorkspace":"C:\/src\/jspwork","name":"hangul.html","lastModified":1590474056201,"locationURI":"file:\/C:\/src\/jspwork\/Chapter3\/WebContent\/hangul.html"},{"path":"\/Servers\/Tomcat v8.5 Server at localhost-config","parentWorkspace":"C:\/src\/jspwork","name":"web.xml","lastModified":1590543533191,"locationURI":"file:\/C:\/src\/jspwork\/Servers\/Tomcat%20v8.5%20Server%20at%20localhost-config\/web.xml"},{"path":"\/ch04\/WebContent","parentWorkspace":"C:\/src\/jspwork","name":"joinProc.jsp","lastModified":1590556191729,"locationURI":"file:\/C:\/src\/jspwork\/ch04\/WebContent\/joinProc.jsp"},{"path":"\/ch04\/src\/ch04","parentWorkspace":"C:\/src\/jspwork","name":"Users.java","lastModified":1590555908528,"locationURI":"file:\/C:\/src\/jspwork\/ch04\/src\/ch04\/Users.java"},{"path":"\/Chapter3\/src","parentWorkspace":"C:\/src\/jspwork","name":"DirectURLServlet.java","lastModified":1590471300982,"locationURI":"file:\/C:\/src\/jspwork\/Chapter3\/src\/DirectURLServlet.java"},{"path":"\/Chapter3\/src","parentWorkspace":"C:\/src\/jspwork","name":"GetNameServlet.java","lastModified":1590476567481,"locationURI":"file:\/C:\/src\/jspwork\/Chapter3\/src\/GetNameServlet.java"},{"path":"\/test\/WebContent","parentWorkspace":"C:\/src\/jspwork","name":"index.html","lastModified":1590132486687,"locationURI":"file:\/C:\/src\/jspwork\/test\/WebContent\/index.html"},{"path":"\/Chapter3\/src","parentWorkspace":"C:\/src\/jspwork","name":"LoginServlet.java","lastModified":1590469499516,"locationURI":"file:\/C:\/src\/jspwork\/Chapter3\/src\/LoginServlet.java"},{"path":"\/ch04\/WebContent","parentWorkspace":"C:\/src\/jspwork","name":"test1.jsp","lastModified":1590543831775,"locationURI":"file:\/C:\/src\/jspwork\/ch04\/WebContent\/test1.jsp"},{"path":"\/ch04\/WebContent","parentWorkspace":"C:\/src\/jspwork","name":"join.jsp","lastModified":1590555642983,"locationURI":"file:\/C:\/src\/jspwork\/ch04\/WebContent\/join.jsp"},{"path":"\/ch04\/src\/ch04","parentWorkspace":"C:\/src\/jspwork","name":"Hello.java","lastModified":1590560865430,"locationURI":"file:\/C:\/src\/jspwork\/ch04\/src\/ch04\/Hello.java"},{"path":"\/test\/src\/com\/cos\/test","parentWorkspace":"C:\/src\/jspwork","name":"Hello.java","lastModified":1590385120922,"locationURI":"file:\/C:\/src\/jspwork\/test\/src\/com\/cos\/test\/Hello.java"},{"path":"\/Chapter3\/src","parentWorkspace":"C:\/src\/jspwork","name":"SessionLoginServlet.java","lastModified":1590477638052,"locationURI":"file:\/C:\/src\/jspwork\/Chapter3\/src\/SessionLoginServlet.java"},{"path":"\/ch04\/WebContent","parentWorkspace":"C:\/src\/jspwork","name":"joinComplete.jsp","lastModified":1590555949115,"locationURI":"file:\/C:\/src\/jspwork\/ch04\/WebContent\/joinComplete.jsp"},{"path":"\/ch04\/WebContent","parentWorkspace":"C:\/src\/jspwork","name":"scriptletTest2.jsp","lastModified":1590546797263,"locationURI":"file:\/C:\/src\/jspwork\/ch04\/WebContent\/scriptletTest2.jsp"},{"path":"\/Chapter3\/WebContent","parentWorkspace":"C:\/src\/jspwork","name":"BoardList.html","lastModified":1590470505219,"locationURI":"file:\/C:\/src\/jspwork\/Chapter3\/WebContent\/BoardList.html"},{"path":"\/Chapter3\/WebContent","parentWorkspace":"C:\/src\/jspwork","name":"dog.html","lastModified":1590475726178,"locationURI":"file:\/C:\/src\/jspwork\/Chapter3\/WebContent\/dog.html"},{"path":"\/ch03\/src\/com\/cos\/ch03","parentWorkspace":"C:\/src\/jspwork","name":"EncServlet.java","lastModified":1590463729249,"locationURI":"file:\/C:\/src\/jspwork\/ch03\/src\/com\/cos\/ch03\/EncServlet.java"},{"path":"\/test\/src\/com\/cos\/test","parentWorkspace":"C:\/src\/jspwork","name":"FrontController.java","lastModified":1590392032025,"locationURI":"file:\/C:\/src\/jspwork\/test\/src\/com\/cos\/test\/FrontController.java"},{"path":"\/Chapter3\/WebContent","parentWorkspace":"C:\/src\/jspwork","name":"memReg.html","lastModified":1590473034954,"locationURI":"file:\/C:\/src\/jspwork\/Chapter3\/WebContent\/memReg.html"},{"path":"\/ch04\/WebContent\/WEB-INF","parentWorkspace":"C:\/src\/jspwork","name":"web.xml","lastModified":1590543433984,"locationURI":"file:\/C:\/src\/jspwork\/ch04\/WebContent\/WEB-INF\/web.xml"},{"path":"\/test\/WebContent","parentWorkspace":"C:\/src\/jspwork","name":"test.jsp","lastModified":1590370824686,"locationURI":"file:\/C:\/src\/jspwork\/test\/WebContent\/test.jsp"},{"path":"\/Chapter3\/WebContent","parentWorkspace":"C:\/src\/jspwork","name":"login.html","lastModified":1590469176544,"locationURI":"file:\/C:\/src\/jspwork\/Chapter3\/WebContent\/login.html"},{"path":"\/ch03\/src\/com\/cos\/ch03","parentWorkspace":"C:\/src\/jspwork","name":"User.java","lastModified":1590463103268,"locationURI":"file:\/C:\/src\/jspwork\/ch03\/src\/com\/cos\/ch03\/User.java"},{"path":"\/Chapter3\/src","parentWorkspace":"C:\/src\/jspwork","name":"ChoiceDogServlet.java","lastModified":1590476082952,"locationURI":"file:\/C:\/src\/jspwork\/Chapter3\/src\/ChoiceDogServlet.java"},{"path":"\/Chapter3\/WebContent","parentWorkspace":"C:\/src\/jspwork","name":"menu.jsp","lastModified":1590477044251,"locationURI":"file:\/C:\/src\/jspwork\/Chapter3\/WebContent\/menu.jsp"},{"path":"\/Chapter3\/src","parentWorkspace":"C:\/src\/jspwork","name":"MemRegServlet.java","lastModified":1590473473865,"locationURI":"file:\/C:\/src\/jspwork\/Chapter3\/src\/MemRegServlet.java"},{"path":"\/ch03\/WebContent","parentWorkspace":"C:\/src\/jspwork","name":"test.html","lastModified":1590457263863,"locationURI":"file:\/C:\/src\/jspwork\/ch03\/WebContent\/test.html"}]}